argparser_ng/README.md
argparser_ng/__init__.py
argparser_ng/parts.py
argparser_ng-1.0.4.dist-info/licenses/LICENSE.md
argparser_ng-1.0.4.dist-info/METADATA
argparser_ng-1.0.4.dist-info/WHEEL
argparser_ng-1.0.4.dist-info/top_level.txt
argparser_ng-1.0.4.dist-info/RECORD
