Metadata-Version: 2.4
Name: argparser-ng
Version: 1.0.4
Summary: NextGen Argument Parser
Author-email: AccidentallyTheCable <cableninja@cableninja.net>
License: GPLv3
Project-URL: Homepage, https://gitlab.com/accidentallythecable-public/python-modules/argparser-ng/
Project-URL: Bug Tracker, https://gitlab.com/accidentallythecable-public/python-modules/argparser-ng/issues
Classifier: Programming Language :: Python :: 3
Classifier: License :: OSI Approved :: GNU General Public License v3 (GPLv3)
Classifier: Environment :: Console
Classifier: Intended Audience :: Developers
Classifier: Operating System :: OS Independent
Classifier: Topic :: Documentation
Classifier: Topic :: Software Development :: Libraries :: Python Modules
Classifier: Topic :: Software Development :: User Interfaces
Classifier: Topic :: Utilities
Classifier: Typing :: Typed
Requires-Python: >=3.11
License-File: LICENSE.md
Dynamic: license-file
